fractal_analysis/__init__.py
fractal_analysis/estimator/__init__.py
fractal_analysis/estimator/hurst_estimator.py
fractal_analysis/simulator/__init__.py
fractal_analysis/simulator/dpw/__init__.py
fractal_analysis/simulator/dpw/dpw_fractal_simulator.py
fractal_analysis/simulator/dpw/dpw_multi_fractal_simulator.py
fractal_analysis/simulator/wood_chan/__init__.py
fractal_analysis/simulator/wood_chan/wood_chan_fractal_simulator.py
fractal_analysis/simulator/wood_chan/wood_chan_multi_fractal_simulator.py
fractal_analysis/tester/__init__.py
fractal_analysis/tester/critical_surface.py
fractal_analysis/tester/estimate_sigma.py
fractal_analysis/tester/series_tester.py
fractal_analysis-0.3.6.dist-info/METADATA
fractal_analysis-0.3.6.dist-info/WHEEL
fractal_analysis-0.3.6.dist-info/licenses/LICENSE
fractal_analysis-0.3.6.dist-info/RECORD
