Metadata-Version: 2.4
Name: fractal-analysis
Version: 0.3.6
Summary: 
License: MIT
License-File: LICENSE
Author: yujiading
Author-email: yujia.ding@cgu.edu
Requires-Python: >=3.13
Classifier: License :: OSI Approved :: MIT License
Classifier: Programming Language :: Python :: 3
Classifier: Programming Language :: Python :: 3.13
Classifier: Programming Language :: Python :: 3.14
Requires-Dist: matplotlib (>=3.10.1,<4.0.0)
Requires-Dist: mpmath (>=1.3.0,<2.0.0)
Requires-Dist: notebook (>=7.3.3,<8.0.0)
Requires-Dist: pandas (>=2.2.3,<3.0.0)
Requires-Dist: scikit-learn (>=1.6.1,<2.0.0)
Requires-Dist: scipy (>=1.15.2,<2.0.0)
Requires-Dist: tqdm (>=4.67.1,<5.0.0)
Project-URL: Homepage, https://github.com/yujiading/fractals
Project-URL: Repository, https://github.com/yujiading/fractals
